<?xml version="1.0"?>
  <database name="TABLE RCQA_CARDINGNEPS">
    <table name="RCQA_CARDINGNEPS" primaryKey="RCQA_CARDINGNEPS_KEY">
      <column name="RCQA_CARDINGNEPS_ID" primaryKey="true" required="true" type="VARCHAR" size="32" autoIncrement="false">
        <default/>
        <onCreateDefault/>
      </column>
      <column name="AD_CLIENT_ID" primaryKey="false" required="true" type="VARCHAR" size="32" autoIncrement="false">
        <default/>
        <onCreateDefault/>
      </column>
      <column name="AD_ORG_ID" primaryKey="false" required="true" type="VARCHAR" size="32" autoIncrement="false">
        <default/>
        <onCreateDefault/>
      </column>
      <column name="ISACTIVE" primaryKey="false" required="true" type="CHAR" size="1" autoIncrement="false">
        <default><![CDATA[Y]]></default>
        <onCreateDefault/>
      </column>
      <column name="CREATED" primaryKey="false" required="true" type="TIMESTAMP" size="7" autoIncrement="false">
        <default><![CDATA[SYSDATE]]></default>
        <onCreateDefault/>
      </column>
      <column name="CREATEDBY" primaryKey="false" required="true" type="VARCHAR" size="32" autoIncrement="false">
        <default/>
        <onCreateDefault/>
      </column>
      <column name="UPDATED" primaryKey="false" required="true" type="TIMESTAMP" size="7" autoIncrement="false">
        <default><![CDATA[SYSDATE]]></default>
        <onCreateDefault/>
      </column>
      <column name="UPDATEDBY" primaryKey="false" required="true" type="VARCHAR" size="32" autoIncrement="false">
        <default/>
        <onCreateDefault/>
      </column>
      <column name="RCPR_COUNT_ID" primaryKey="false" required="false" type="VARCHAR" size="32" autoIncrement="false">
        <default/>
        <onCreateDefault/>
      </column>
      <column name="RCPR_MACHINE_ID" primaryKey="false" required="true" type="VARCHAR" size="32" autoIncrement="false">
        <default/>
        <onCreateDefault/>
      </column>
      <column name="DATE" primaryKey="false" required="true" type="TIMESTAMP" size="7" autoIncrement="false">
        <default/>
        <onCreateDefault/>
      </column>
      <column name="RCPR_SHED_ID" primaryKey="false" required="true" type="VARCHAR" size="32" autoIncrement="false">
        <default/>
        <onCreateDefault/>
      </column>
      <column name="RCPR_MACHINEPROCESS_ID" primaryKey="false" required="true" type="VARCHAR" size="32" autoIncrement="false">
        <default/>
        <onCreateDefault/>
      </column>
      <column name="HANK" primaryKey="false" required="false" type="DECIMAL" size="10,2" autoIncrement="false">
        <default/>
        <onCreateDefault/>
      </column>
      <column name="SPEED" primaryKey="false" required="false" type="DECIMAL" size="10,0" autoIncrement="false">
        <default/>
        <onCreateDefault/>
      </column>
      <column name="CHUTENEPS" primaryKey="false" required="false" type="DECIMAL" size="10,0" autoIncrement="false">
        <default/>
        <onCreateDefault/>
      </column>
      <column name="SLIVERNEPS" primaryKey="false" required="false" type="DECIMAL" size="10,0" autoIncrement="false">
        <default/>
        <onCreateDefault/>
      </column>
      <column name="NRE" primaryKey="false" required="false" type="DECIMAL" size="10,2" autoIncrement="false">
        <default/>
        <onCreateDefault/>
      </column>
      <column name="RCPR_COUNTMASTER_ID" primaryKey="false" required="false" type="VARCHAR" size="32" autoIncrement="false">
        <default/>
        <onCreateDefault/>
      </column>
      <foreign-key foreignTable="AD_CLIENT" name="RCQA_CARDINGNEPS_CLIENT">
        <reference local="AD_CLIENT_ID" foreign="AD_CLIENT_ID"/>
      </foreign-key>
      <foreign-key foreignTable="RCPR_COUNT" name="RCQA_CARDINGNEPS_COUNT">
        <reference local="RCPR_COUNT_ID" foreign="RCPR_COUNT_ID"/>
      </foreign-key>
      <foreign-key foreignTable="RCPR_COUNTMASTER" name="RCQA_CARDINGNEPS_COUNTMAS">
        <reference local="RCPR_COUNTMASTER_ID" foreign="RCPR_COUNTMASTER_ID"/>
      </foreign-key>
      <foreign-key foreignTable="RCPR_MACHINE" name="RCQA_CARDINGNEPS_MACHINE">
        <reference local="RCPR_MACHINE_ID" foreign="RCPR_MACHINE_ID"/>
      </foreign-key>
      <foreign-key foreignTable="RCPR_MACHINEPROCESS" name="RCQA_CARDINGNEPS_MACHINEPRO">
        <reference local="RCPR_MACHINEPROCESS_ID" foreign="RCPR_MACHINEPROCESS_ID"/>
      </foreign-key>
      <foreign-key foreignTable="AD_ORG" name="RCQA_CARDINGNEPS_ORG">
        <reference local="AD_ORG_ID" foreign="AD_ORG_ID"/>
      </foreign-key>
      <foreign-key foreignTable="RCPR_SHED" name="RCQA_CARDINGNEPS_SHED">
        <reference local="RCPR_SHED_ID" foreign="RCPR_SHED_ID"/>
      </foreign-key>
    </table>
  </database>
